flask_project_creator/__init__.py
flask_project_creator-0.1.2.dist-info/METADATA
flask_project_creator-0.1.2.dist-info/WHEEL
flask_project_creator-0.1.2.dist-info/entry_points.txt
flask_project_creator-0.1.2.dist-info/top_level.txt
flask_project_creator-0.1.2.dist-info/RECORD
