Metadata-Version: 2.1
Name: flask_project_creator
Version: 0.1.2
Summary: Flask Project Creator: A CLI tool for quickly setting up Flask web applications.
Author: Omkar Subhash Parab
Author-email: omkar211196@gmail.com
Requires-Dist: click
Requires-Dist: flask
